biometrics_client/__init__.py
biometrics_client/_utils.py
biometrics_client/client.py
biometrics_client/exceptions.py
tests/_fixtures/__init__.py
eh_biometrics_client-0.0.1.dist-info/LICENSE.txt
eh_biometrics_client-0.0.1.dist-info/METADATA
eh_biometrics_client-0.0.1.dist-info/WHEEL
eh_biometrics_client-0.0.1.dist-info/top_level.txt
eh_biometrics_client-0.0.1.dist-info/RECORD
