Metadata-Version: 2.1
Name: eh-biometrics-client
Version: 0.0.1
Summary: # Biometrics Client
Requires-Dist: requests (==2.22.0)
Requires-Dist: requests-toolbelt (==0.9.1)
Provides-Extra: test
Requires-Dist: pytest ; extra == 'test'
Requires-Dist: coverage ; extra == 'test'
